stubdoc/__init__.py
stubdoc/cli.py
stubdoc/stubdoc.py
stubdoc-0.1.12.dist-info/LICENSE
stubdoc-0.1.12.dist-info/METADATA
stubdoc-0.1.12.dist-info/WHEEL
stubdoc-0.1.12.dist-info/entry_points.txt
stubdoc-0.1.12.dist-info/top_level.txt
stubdoc-0.1.12.dist-info/RECORD
