Metadata-Version: 2.1
Name: stubdoc
Version: 0.1.12
Summary: stubdoc is a Python library that append docstring to stub files.
Home-page: https://github.com/simon-ritchie/stubdoc/tree/main
Maintainer: simon-ritchie
Maintainer-email: 
License: MIT
Classifier: Programming Language :: Python :: 3
Classifier: License :: OSI Approved :: MIT License
License-File: LICENSE
